Metadata-Version: 2.1
Name: sentry-dingtalk-jedore
Version: 1.0.7
Summary: A sentry extension integrates DingTalk robot webhook
Home-page: https://github.com/Jedore/sentry-dingtalk
Author: Jedore
Author-email: jedorefight@gmail.com
License: MIT
Keywords: sentry dingtalk
Platform: UNKNOWN
Classifier: License :: OSI Approved :: MIT License
Classifier: Programming Language :: Python
Classifier: Programming Language :: Python :: 3
Classifier: Programming Language :: Python :: 3.6
Classifier: Programming Language :: Python :: 3.7
Classifier: Programming Language :: Python :: Implementation :: CPython
Requires-Python: >=3.6.13
Requires-Dist: sentry (>=21.5.1)
